_rtl/pwm_unit.v
//------------------------------------------------------------------------------
// pwm_unit.v — Módulo PWM sencillo (Verilog-2001)
//------------------------------------------------------------------------------

module pwm_unit #(
  parameter CNT_WIDTH = 16,
  parameter DUTY_WIDTH = 16
)(
  input                      clk_i,
  input                      rst_ni,
  input  [CNT_WIDTH-1:0]     cfg_period,
  input  [DUTY_WIDTH-1:0]    cfg_duty,
  output                     pwm_o
);

  reg [CNT_WIDTH-1:0] cnt;

  // Contador principal
  always @(posedge clk_i or negedge rst_ni) begin
    if (!rst_ni)
      cnt <= 0;
    else if (cnt >= cfg_period - 1)
      cnt <= 0;
    else
      cnt <= cnt + 1;
  end

  // Lógica PWM
  assign pwm_o = (cnt < cfg_duty);

endmodule

tb/_tb/tb_pwm_unit.v
`timescale 1ns/1ps

module tb_pwm_unit;

    // Parámetros igual que el módulo
    localparam CNT_WIDTH   = 16;
    localparam DUTY_WIDTH  = 16;

    reg clk_i;
    reg rst_ni;
    reg [CNT_WIDTH-1:0] cfg_period;
    reg [DUTY_WIDTH-1:0] cfg_duty;
    wire pwm_o;

    // Instancia del DUT
    pwm_unit #(
        .CNT_WIDTH(CNT_WIDTH),
        .DUTY_WIDTH(DUTY_WIDTH)
    ) dut (
        .clk_i(clk_i),
        .rst_ni(rst_ni),
        .cfg_period(cfg_period),
        .cfg_duty(cfg_duty),
        .pwm_o(pwm_o)
    );

    // Generador de reloj
    always #5 clk_i = ~clk_i;

    initial begin
        clk_i = 0;
        rst_ni = 0;
        cfg_period = 10;
        cfg_duty = 4;

        // Aplica reset
        #12;
        rst_ni = 1;

        // Espera para ver la forma de onda PWM con duty=4/10
        #120;

        // Cambia duty a 7 (PWM ON 7/10 del tiempo)
        cfg_duty = 7;
        #100;

        // Cambia el periodo a 16, duty a 8
        cfg_period = 16;
        cfg_duty = 8;
        #160;

        // Prueba duty=0 y duty=period
        cfg_duty = 0; // PWM siempre en 0
        #20;
        cfg_duty = 16; // PWM siempre en 1 (period = 16)
        #20;

        $finish;
    end

    // Guardar forma de onda y monitoreo básico
    initial begin
        $dumpfile("tb/tb_pwm_unit.vcd");
        $dumpvars(0, tb_pwm_unit);
        $display("time\tpwm_o");
        $monitor("%g\t%b", $time, pwm_o);
    end

endmodule

tb/tb_pwm_unit.vcd
$date
	Thu Jul 24 14:11:28 2025
$end
$version
	Icarus Verilog
$end
$timescale
	1ps
$end
$scope module tb_pwm_unit $end
$var wire 1 ! pwm_o $end
$var parameter 32 " CNT_WIDTH $end
$var parameter 32 # DUTY_WIDTH $end
$var reg 16 $ cfg_duty [15:0] $end
$var reg 16 % cfg_period [15:0] $end
$var reg 1 & clk_i $end
$var reg 1 ' rst_ni $end
$scope module dut $end
$var wire 16 ( cfg_duty [15:0] $end
$var wire 16 ) cfg_period [15:0] $end
$var wire 1 & clk_i $end
$var wire 1 ' rst_ni $end
$var wire 1 ! pwm_o $end
$var parameter 32 * CNT_WIDTH $end
$var parameter 32 + DUTY_WIDTH $end
$var reg 16 , cnt [15:0] $end
$upscope $end
$upscope $end
$enddefinitions $end
$comment Show the parameter values. $end
$dumpall
b10000 +
b10000 *
b10000 #
b10000 "
$end
#0
$dumpvars
b0 ,
b1010 )
b100 (
0'
0&
b1010 %
b100 $
1!
$end
#5000
1&
#10000
0&
#12000
1'
#15000
b1 ,
1&
#20000
0&
#25000
b10 ,
1&
#30000
0&
#35000
b11 ,
1&
#40000
0&
#45000
0!
b100 ,
1&
#50000
0&
#55000
b101 ,
1&
#60000
0&
#65000
b110 ,
1&
#70000
0&
#75000
b111 ,
1&
#80000
0&
#85000
b1000 ,
1&
#90000
0&
#95000
b1001 ,
1&
#100000
0&
#105000
1!
b0 ,
1&
#110000
0&
#115000
b1 ,
1&
#120000
0&
#125000
b10 ,
1&
#130000
0&
#132000
b111 $
b111 (
#135000
b11 ,
1&
#140000
0&
#145000
b100 ,
1&
#150000
0&
#155000
b101 ,
1&
#160000
0&
#165000
b110 ,
1&
#170000
0&
#175000
0!
b111 ,
1&
#180000
0&
#185000
b1000 ,
1&
#190000
0&
#195000
b1001 ,
1&
#200000
0&
#205000
1!
b0 ,
1&
#210000
0&
#215000
b1 ,
1&
#220000
0&
#225000
b10 ,
1&
#230000
0&
#232000
b1000 $
b1000 (
b10000 %
b10000 )
#235000
b11 ,
1&
#240000
0&
#245000
b100 ,
1&
#250000
0&
#255000
b101 ,
1&
#260000
0&
#265000
b110 ,
1&
#270000
0&
#275000
b111 ,
1&
#280000
0&
#285000
0!
b1000 ,
1&
#290000
0&
#295000
b1001 ,
1&
#300000
0&
#305000
b1010 ,
1&
#310000
0&
#315000
b1011 ,
1&
#320000
0&
#325000
b1100 ,
1&
#330000
0&
#335000
b1101 ,
1&
#340000
0&
#345000
b1110 ,
1&
#350000
0&
#355000
b1111 ,
1&
#360000
0&
#365000
1!
b0 ,
1&
#370000
0&
#375000
b1 ,
1&
#380000
0&
#385000
b10 ,
1&
#390000
0&
#392000
0!
b0 $
b0 (
#395000
b11 ,
1&
#400000
0&
#405000
b100 ,
1&
#410000
0&
#412000
1!
b10000 $
b10000 (
#415000
b101 ,
1&
#420000
0&
#425000
b110 ,
1&
