rtl/reg_iface.v
//------------------------------------------------------------------------------
// reg_iface.v — Interfaz de registro con nombres modificados (Verilog-2001)
//------------------------------------------------------------------------------
module reg_iface (
  clk_i,
  rst_ni,
  addr_i,
  wr_data_i,
  rd_data_o,
  wr_en_i,
  rd_en_i,
  ctrl_o,
  status_in_i,
  status_o
);
  parameter AW = 8;
  parameter DW = 32;

  input                   clk_i;
  input                   rst_ni;
  input  [AW-1:0]         addr_i;
  input  [DW-1:0]         wr_data_i;
  output [DW-1:0]         rd_data_o;
  input                   wr_en_i;
  input                   rd_en_i;
  output [DW-1:0]         ctrl_o;
  input  [DW-1:0]         status_in_i;
  output [DW-1:0]         status_o;

  // Offsets locales
  localparam [AW-1:0] CTRL_ADDR   = 8'h00;
  localparam [AW-1:0] STATUS_ADDR = 8'h04;

  reg [DW-1:0] ctrl_reg;
  reg [DW-1:0] status_reg;
  reg [DW-1:0] rd_data_reg;

  // Escritura y actualización de status
  always @(posedge clk_i or negedge rst_ni) begin
    if (!rst_ni) begin
      ctrl_reg   <= {DW{1'b0}};
      status_reg <= {DW{1'b0}};
    end else begin
      status_reg <= status_in_i;
      if (wr_en_i) begin
        case (addr_i)
          CTRL_ADDR: ctrl_reg <= wr_data_i;
          default: /* noop */ ;
        endcase
      end
    end
  end

  // Lectura
  always @(*) begin
    if (rd_en_i) begin
      case (addr_i)
        CTRL_ADDR:   rd_data_reg = ctrl_reg;
        STATUS_ADDR: rd_data_reg = status_reg;
        default:     rd_data_reg = {DW{1'b0}};
      endcase
    end else begin
      rd_data_reg = {DW{1'b0}};
    end
  end

  assign ctrl_o   = ctrl_reg;
  assign status_o = status_reg;
  assign rd_data_o = rd_data_reg;

endmodule

tb/_tb/tb_reg_iface.v
`timescale 1ns/1ps

module tb_reg_iface;

    localparam AW = 8;
    localparam DW = 32;

    reg clk_i;
    reg rst_ni;
    reg [AW-1:0] addr_i;
    reg [DW-1:0] wr_data_i;
    wire [DW-1:0] rd_data_o;
    reg wr_en_i;
    reg rd_en_i;
    wire [DW-1:0] ctrl_o;
    reg  [DW-1:0] status_in_i;
    wire [DW-1:0] status_o;

    // Instancia del DUT
    reg_iface dut (
        .clk_i(clk_i),
        .rst_ni(rst_ni),
        .addr_i(addr_i),
        .wr_data_i(wr_data_i),
        .rd_data_o(rd_data_o),
        .wr_en_i(wr_en_i),
        .rd_en_i(rd_en_i),
        .ctrl_o(ctrl_o),
        .status_in_i(status_in_i),
        .status_o(status_o)
    );

    // Generador de reloj
    always #5 clk_i = ~clk_i;

    initial begin
        clk_i = 0;
        rst_ni = 0;
        addr_i = 0;
        wr_data_i = 0;
        wr_en_i = 0;
        rd_en_i = 0;
        status_in_i = 0;

        // Reset
        #10;
        rst_ni = 1;

        // Escribe en ctrl (addr = 0)
        @(negedge clk_i);
        addr_i = 8'h00;
        wr_data_i = 32'h000000FF;
        wr_en_i = 1;
        @(negedge clk_i);
        wr_en_i = 0;

        // Lee ctrl
        @(negedge clk_i);
        rd_en_i = 1;
        addr_i = 8'h00;
        @(negedge clk_i);
        rd_en_i = 0;

        // Actualiza status
        @(negedge clk_i);
        status_in_i = 32'hA5A5A5A5;

        // Lee status
        @(negedge clk_i);
        rd_en_i = 1;
        addr_i = 8'h04;
        @(negedge clk_i);
        rd_en_i = 0;

        // Reset de nuevo
        #10;
        rst_ni = 0;
        @(negedge clk_i);
        rst_ni = 1;

        // Lee ctrl
        @(negedge clk_i);
        rd_en_i = 1;
        addr_i = 8'h00;
        @(negedge clk_i);
        rd_en_i = 0;

        // Lee status
        @(negedge clk_i);
        rd_en_i = 1;
        addr_i = 8'h04;
        @(negedge clk_i);
        rd_en_i = 0;

        #20;
        $finish;
    end

    // Dump de señales
    initial begin
        $dumpfile("tb/tb_reg_iface.vcd");
        $dumpvars(0, tb_reg_iface);
        $display("time\tctrl_o\trd_data_o\tstatus_o");
        $monitor("%g\t%h\t%h\t%h", $time, ctrl_o, rd_data_o, status_o);
    end

endmodule

tb/tb_reg_iface.vcd
$date
	Thu Jul 24 14:16:20 2025
$end
$version
	Icarus Verilog
$end
$timescale
	1ps
$end
$scope module tb_reg_iface $end
$var wire 32 ! status_o [31:0] $end
$var wire 32 " rd_data_o [31:0] $end
$var wire 32 # ctrl_o [31:0] $end
$var parameter 32 $ AW $end
$var parameter 32 % DW $end
$var reg 8 & addr_i [7:0] $end
$var reg 1 ' clk_i $end
$var reg 1 ( rd_en_i $end
$var reg 1 ) rst_ni $end
$var reg 32 * status_in_i [31:0] $end
$var reg 32 + wr_data_i [31:0] $end
$var reg 1 , wr_en_i $end
$scope module dut $end
$var wire 8 - addr_i [7:0] $end
$var wire 1 ' clk_i $end
$var wire 32 . ctrl_o [31:0] $end
$var wire 32 / rd_data_o [31:0] $end
$var wire 1 ( rd_en_i $end
$var wire 1 ) rst_ni $end
$var wire 32 0 status_in_i [31:0] $end
$var wire 32 1 status_o [31:0] $end
$var wire 32 2 wr_data_i [31:0] $end
$var wire 1 , wr_en_i $end
$var parameter 32 3 AW $end
$var parameter 8 4 CTRL_ADDR $end
$var parameter 32 5 DW $end
$var parameter 8 6 STATUS_ADDR $end
$var reg 32 7 ctrl_reg [31:0] $end
$var reg 32 8 rd_data_reg [31:0] $end
$var reg 32 9 status_reg [31:0] $end
$upscope $end
$upscope $end
$enddefinitions $end
$comment Show the parameter values. $end
$dumpall
b100 6
b100000 5
b0 4
b1000 3
b100000 %
b1000 $
$end
#0
$dumpvars
b0 9
b0 8
b0 7
b0 2
b0 1
b0 0
b0 /
b0 .
b0 -
0,
b0 +
b0 *
0)
0(
0'
b0 &
b0 #
b0 "
b0 !
$end
#5000
1'
#10000
1,
b11111111 +
b11111111 2
0'
1)
#15000
b11111111 #
b11111111 .
b11111111 7
1'
#20000
0,
0'
#25000
1'
#30000
b11111111 "
b11111111 /
b11111111 8
1(
0'
#35000
1'
#40000
b0 "
b0 /
b0 8
0(
0'
#45000
1'
#50000
b10100101101001011010010110100101 *
b10100101101001011010010110100101 0
0'
#55000
b10100101101001011010010110100101 !
b10100101101001011010010110100101 1
b10100101101001011010010110100101 9
1'
#60000
b10100101101001011010010110100101 "
b10100101101001011010010110100101 /
b10100101101001011010010110100101 8
b100 &
b100 -
1(
0'
#65000
1'
#70000
b0 "
b0 /
b0 8
0(
0'
#75000
1'
#80000
b0 !
b0 1
b0 9
b0 #
b0 .
b0 7
0'
1)
#85000
b10100101101001011010010110100101 !
b10100101101001011010010110100101 1
b10100101101001011010010110100101 9
1'
#90000
b0 &
b0 -
1(
0'
#95000
1'
#100000
0(
0'
#105000
1'
#110000
b10100101101001011010010110100101 "
b10100101101001011010010110100101 /
b10100101101001011010010110100101 8
b100 &
b100 -
1(
0'
#115000
1'
#120000
b0 "
b0 /
b0 8
0(
0'
